megatron/__init__.py
megatron/arguments.py
megatron/checkpointing.py
megatron/global_vars.py
megatron/indexer.py
megatron/initialize.py
megatron/learning_rates.py
megatron/memory.py
megatron/microbatches.py
megatron/package_info.py
megatron/text_generation_utils.py
megatron/training.py
megatron/utils.py
megatron/data/Makefile
megatron/data/__init__.py
megatron/data/bert_dataset.py
megatron/data/blendable_dataset.py
megatron/data/data_loaders.py
megatron/data/dataset_utils.py
megatron/data/gpt_dataset.py
megatron/data/helpers.cpp
megatron/data/ict_dataset.py
megatron/data/indexed_dataset.py
megatron/data/realm_dataset_utils.py
megatron/data/realm_index.py
megatron/fused_kernels/__init__.py
megatron/model/__init__.py
megatron/model/bert_model.py
megatron/model/classification.py
megatron/model/distributed.py
megatron/model/fused_bias_gelu.py
megatron/model/fused_layer_norm.py
megatron/model/fused_softmax.py
megatron/model/gpt_model.py
megatron/model/language_model.py
megatron/model/module.py
megatron/model/multiple_choice.py
megatron/model/realm_model.py
megatron/model/transformer.py
megatron/model/utils.py
megatron/mpu/__init__.py
megatron/mpu/cross_entropy.py
megatron/mpu/data.py
megatron/mpu/initialize.py
megatron/mpu/layers.py
megatron/mpu/mappings.py
megatron/mpu/random.py
megatron/mpu/utils.py
megatron/mpu/tests/__init__.py
megatron/mpu/tests/commons.py
megatron/mpu/tests/test_cross_entropy.py
megatron/mpu/tests/test_data.py
megatron/mpu/tests/test_initialize.py
megatron/mpu/tests/test_layers.py
megatron/mpu/tests/test_random.py
megatron/optimizer/__init__.py
megatron/optimizer/clip_grads.py
megatron/optimizer/grad_scaler.py
megatron/optimizer/optimizer.py
megatron/tokenizer/__init__.py
megatron/tokenizer/bert_tokenization.py
megatron/tokenizer/gpt2_tokenization.py
megatron/tokenizer/tokenizer.py
megatron_lm-2.2.0.dist-info/LICENSE
megatron_lm-2.2.0.dist-info/METADATA
megatron_lm-2.2.0.dist-info/WHEEL
megatron_lm-2.2.0.dist-info/top_level.txt
megatron_lm-2.2.0.dist-info/RECORD
