Metadata-Version: 2.1
Name: megatron-lm
Version: 2.2.0
Summary: Megatron-LM: Training Multi-Billion Parameter Language Models Using Model Parallelism.
Home-page: https://github.com/NVIDIA/Megatron-LM
Author: NVIDIA INC
Maintainer: NVIDIA INC
License: See https://github.com/NVIDIA/Megatron-LM/blob/master/LICENSE
Keywords: deep learning,Megatron,gpu,NLP,nvidia,pytorch,torch,language
Platform: UNKNOWN
Classifier: Intended Audience :: Developers
Classifier: Intended Audience :: Science/Research
Classifier: Intended Audience :: Information Technology
Classifier: Topic :: Scientific/Engineering :: Artificial Intelligence
Classifier: Topic :: Software Development :: Libraries :: Python Modules
Classifier: Programming Language :: Python :: 3.6
Classifier: Programming Language :: Python :: 3.7
Classifier: Programming Language :: Python :: 3.8
Classifier: Environment :: Console
Classifier: Natural Language :: English
Classifier: Operating System :: OS Independent
Requires-Python: >=3.6
Requires-Dist: pybind11
Requires-Dist: torch
Requires-Dist: six
Requires-Dist: regex
Requires-Dist: numpy
